front/__init__.py
front/base.py
front/session_state.py
front/util.py
front/examples/__init__.py
front/examples/simple.py
front-0.0.4.dist-info/LICENSE
front-0.0.4.dist-info/METADATA
front-0.0.4.dist-info/WHEEL
front-0.0.4.dist-info/top_level.txt
front-0.0.4.dist-info/RECORD
