Metadata-Version: 2.1
Name: front
Version: 0.0.4
Summary: Getting from python objects to UIs exposing them
Home-page: https://github.com/i2mint/front
Author: OtoSense
License: apache-2.0
Platform: any
Requires-Dist: streamlit
